{"type":"PR","pr":{"number":58,"head":"337f4fd3161badd6ae606c077ccc23a4c9dc6865"},"user":"na.seo.user","status":"draft","branch":"cms/oxygen-collaudo-“in-progress”","collection":"blog-it","title":"Oxygen: collaudo “in progress”","description":"No Description!","objects":{"entry":{"path":"data/posts_it/oxygen-collaudo-“in-progress”.json","sha":"ef500da6d9f0c46f93aa23ea7b601144a1416897"},"files":[{"path":"/src/images/uploads/2019n01next.jpg","sha":"0e8f07ce15e91825bfa06973483e50033b102c8d"}]},"timeStamp":"2019-10-30T12:48:14.595Z"}